user_util/__init__.py
user_util/cli.py
user_util/user_util.py
user_util-2.0.0.dist-info/licenses/AUTHORS.rst
user_util-2.0.0.dist-info/licenses/LICENSE
user_util-2.0.0.dist-info/METADATA
user_util-2.0.0.dist-info/WHEEL
user_util-2.0.0.dist-info/entry_points.txt
user_util-2.0.0.dist-info/top_level.txt
user_util-2.0.0.dist-info/RECORD
