Metadata-Version: 2.4
Name: user_util
Version: 2.0.0
Summary: User utilities for the Open edX platform
Home-page: https://github.com/openedx/user-util
Author: edX
Author-email: oscm@edx.org
License: GNU General Public License v3
Keywords: user_util
Classifier: Development Status :: 2 - Pre-Alpha
Classifier: Intended Audience :: Developers
Classifier: License :: OSI Approved :: GNU General Public License v3 (GPLv3)
Classifier: Natural Language :: English
Classifier: Programming Language :: Python :: 3
Classifier: Programming Language :: Python :: 3.11
Classifier: Programming Language :: Python :: 3.12
License-File: LICENSE
License-File: AUTHORS.rst
Requires-Dist: Click
Dynamic: author
Dynamic: author-email
Dynamic: classifier
Dynamic: description
Dynamic: home-page
Dynamic: keywords
Dynamic: license
Dynamic: license-file
Dynamic: requires-dist
Dynamic: summary
